defaultenv.py
defaultenv-0.0.14.dist-info/LICENSE
defaultenv-0.0.14.dist-info/WHEEL
defaultenv-0.0.14.dist-info/METADATA
defaultenv-0.0.14.dist-info/RECORD
