Metadata-Version: 2.1
Name: defaultenv
Version: 0.0.14
Summary: Environment and .env file reader
Home-page: http://github.com/bobuk/defaultenv
Author: Grigory Bakunov
Author-email: thebobuk@ya.ru
Requires-Python: >=3.0,<4.0
Classifier: Development Status :: 4 - Beta
Classifier: Environment :: Other Environment
Classifier: Intended Audience :: Developers
Classifier: Operating System :: OS Independent
Classifier: Programming Language :: Python
Classifier: Programming Language :: Python :: 3
Classifier: Programming Language :: Python :: 3.4
Classifier: Programming Language :: Python :: 3.5
Classifier: Programming Language :: Python :: 3.6
Classifier: Programming Language :: Python :: 3.7
Classifier: Programming Language :: Python :: 3.8
Classifier: Topic :: Software Development :: Libraries :: Python Modules
Project-URL: Repository, http://github.com/bobuk/defaultenv
